LICENSE.txt
README.md
setup.py
PyPrintLpr.egg-info/PKG-INFO
PyPrintLpr.egg-info/SOURCES.txt
PyPrintLpr.egg-info/dependency_links.txt
PyPrintLpr.egg-info/entry_points.txt
PyPrintLpr.egg-info/requires.txt
PyPrintLpr.egg-info/top_level.txt
pyprintlpr/__init__.py
pyprintlpr/__main__.py
pyprintlpr/__version__.py
pyprintlpr/client.py
pyprintlpr/server_proxy.py