Metadata-Version: 2.4
Name: PyPrintLpr
Version: 1.0.3
Summary: RFC 1179 client and server toolkits and Python library for interacting with printers via LPR protocol or RAW mode, as well as a proxy/server for debugging, job capture, and protocol analysis.
Home-page: https://github.com/Ircama/PyPrintLpr
Author: Ircama
License: EUPL-1.2
Keywords: shell console tkinter
Classifier: Programming Language :: Python :: 3
Classifier: License :: OSI Approved :: European Union Public Licence 1.2 (EUPL 1.2)
Classifier: Topic :: Software Development :: Libraries :: Python Modules
Classifier: Development Status :: 5 - Production/Stable
Classifier: Operating System :: OS Independent
Classifier: Intended Audience :: Developers
Requires-Python: >3.6
License-File: LICENSE.txt
Requires-Dist: hexdump2
Requires-Dist: pyyaml
Dynamic: author
Dynamic: classifier
Dynamic: description
Dynamic: description-content-type
Dynamic: home-page
Dynamic: keywords
Dynamic: license
Dynamic: license-file
Dynamic: requires-dist
Dynamic: requires-python
Dynamic: summary
